kolibri_exercise_perseus_plugin/__init__.py
kolibri_exercise_perseus_plugin/kolibri_plugin.py
kolibri_exercise_perseus_plugin/build/kolibri_exercise_perseus_plugin.main_stats.json
kolibri_exercise_perseus_plugin/locale/ach_UG/LC_MESSAGES/kolibri_exercise_perseus_plugin.main-messages.json
kolibri_exercise_perseus_plugin/locale/ar/LC_MESSAGES/kolibri_exercise_perseus_plugin.main-messages.json
kolibri_exercise_perseus_plugin/locale/bg_BG/LC_MESSAGES/kolibri_exercise_perseus_plugin.main-messages.json
kolibri_exercise_perseus_plugin/locale/bn_BD/LC_MESSAGES/kolibri_exercise_perseus_plugin.main-messages.json
kolibri_exercise_perseus_plugin/locale/de/LC_MESSAGES/kolibri_exercise_perseus_plugin.main-messages.json
kolibri_exercise_perseus_plugin/locale/en/LC_MESSAGES/kolibri_exercise_perseus_plugin.main-messages.json
kolibri_exercise_perseus_plugin/locale/en/LC_MESSAGES/profiles/kolibri_exercise_perseus_plugin.main.json
kolibri_exercise_perseus_plugin/locale/es_419/LC_MESSAGES/kolibri_exercise_perseus_plugin.main-messages.json
kolibri_exercise_perseus_plugin/locale/es_ES/LC_MESSAGES/kolibri_exercise_perseus_plugin.main-messages.json
kolibri_exercise_perseus_plugin/locale/fa/LC_MESSAGES/kolibri_exercise_perseus_plugin.main-messages.json
kolibri_exercise_perseus_plugin/locale/ff_CM/LC_MESSAGES/kolibri_exercise_perseus_plugin.main-messages.json
kolibri_exercise_perseus_plugin/locale/fr_FR/LC_MESSAGES/kolibri_exercise_perseus_plugin.main-messages.json
kolibri_exercise_perseus_plugin/locale/gu_IN/LC_MESSAGES/kolibri_exercise_perseus_plugin.main-messages.json
kolibri_exercise_perseus_plugin/locale/hi_IN/LC_MESSAGES/kolibri_exercise_perseus_plugin.main-messages.json
kolibri_exercise_perseus_plugin/locale/it/LC_MESSAGES/kolibri_exercise_perseus_plugin.main-messages.json
kolibri_exercise_perseus_plugin/locale/km/LC_MESSAGES/kolibri_exercise_perseus_plugin.main-messages.json
kolibri_exercise_perseus_plugin/locale/ko/LC_MESSAGES/kolibri_exercise_perseus_plugin.main-messages.json
kolibri_exercise_perseus_plugin-1.3.5.dist-info/AUTHORS.rst
kolibri_exercise_perseus_plugin-1.3.5.dist-info/LICENSE
kolibri_exercise_perseus_plugin-1.3.5.dist-info/METADATA
kolibri_exercise_perseus_plugin-1.3.5.dist-info/WHEEL
kolibri_exercise_perseus_plugin-1.3.5.dist-info/entry_points.txt
kolibri_exercise_perseus_plugin-1.3.5.dist-info/top_level.txt
kolibri_exercise_perseus_plugin-1.3.5.dist-info/RECORD
