Metadata-Version: 2.1
Name: kolibri-exercise-perseus-plugin
Version: 1.3.5
Summary: Kolibri plugin for rendering Khan Academy Perseus style exercises
Home-page: https://github.com/learningequality/kolibri-exercise-perseus-plugin
Author: Learning Equality
Author-email: info@learningequality.org
License: MIT
Keywords: k,o,l,i,b,r,i
Platform: UNKNOWN
Classifier: Development Status :: 2 - Pre-Alpha
Classifier: Intended Audience :: Developers
Classifier: License :: OSI Approved :: MIT License
Classifier: Natural Language :: English
Classifier: Programming Language :: Python :: 2
Classifier: Programming Language :: Python :: 2.7
Classifier: Programming Language :: Python :: 3
Classifier: Programming Language :: Python :: 3.3
Classifier: Programming Language :: Python :: 3.4
Classifier: Programming Language :: Python :: 3.5
Classifier: Programming Language :: Python :: Implementation :: PyPy
